acto_pytoolkit-0.4.0.dist-info/licenses/LICENSE
pytoolkit/__init__.py
pytoolkit/async_http_client.py
pytoolkit/cache.py
pytoolkit/cli.py
pytoolkit/config_loader.py
pytoolkit/context_utils.py
pytoolkit/crypto_utils.py
pytoolkit/env.py
pytoolkit/file_utils.py
pytoolkit/http_client.py
pytoolkit/logger.py
pytoolkit/math_tools.py
pytoolkit/py.typed
pytoolkit/retry.py
pytoolkit/serialization.py
pytoolkit/string_tools.py
pytoolkit/task_scheduler.py
pytoolkit/timer.py
pytoolkit/validators.py
acto_pytoolkit-0.4.0.dist-info/METADATA
acto_pytoolkit-0.4.0.dist-info/WHEEL
acto_pytoolkit-0.4.0.dist-info/entry_points.txt
acto_pytoolkit-0.4.0.dist-info/top_level.txt
acto_pytoolkit-0.4.0.dist-info/RECORD
