Metadata-Version: 2.4
Name: acto-pytoolkit
Version: 0.4.0
Summary: A collection of helper utilities for Python projects.
Author: pytoolkit contributors
License: MIT License
Project-URL: Homepage, https://www.actobotics.net
Project-URL: Repository, https://github.com/actobotics/pyToolkit
Project-URL: Documentation, https://github.com/actobotics/pyToolkit#readme
Project-URL: Issues, https://github.com/actobotics/pyToolkit/issues
Keywords: utilities,helpers,toolkit,library
Requires-Python: >=3.9
License-File: LICENSE
Requires-Dist: requests>=2.31.0
Requires-Dist: python-dotenv>=1.0.0
Requires-Dist: PyYAML>=6.0.0
Provides-Extra: dev
Requires-Dist: pytest>=7.4.0; extra == "dev"
Requires-Dist: pytest-cov>=4.1.0; extra == "dev"
Requires-Dist: pytest-asyncio>=0.23.0; extra == "dev"
Requires-Dist: mypy>=1.8.0; extra == "dev"
Requires-Dist: black>=24.0.0; extra == "dev"
Requires-Dist: ruff>=0.6.0; extra == "dev"
Requires-Dist: pre-commit>=3.6.0; extra == "dev"
Requires-Dist: types-requests>=2.31.0; extra == "dev"
Requires-Dist: types-PyYAML>=6.0.0; extra == "dev"
Provides-Extra: async
Requires-Dist: aiohttp>=3.9.0; extra == "async"
Requires-Dist: aiofiles>=23.0.0; extra == "async"
Provides-Extra: docs
Requires-Dist: sphinx>=7.2.0; extra == "docs"
Requires-Dist: sphinx-rtd-theme>=2.0.0; extra == "docs"
Requires-Dist: sphinx-autodoc-typehints>=1.25.0; extra == "docs"
Provides-Extra: all
Requires-Dist: pytoolkit[async,dev,docs]; extra == "all"
Dynamic: license-file
